adafruit_circuitpython_mcp3421-1.1.5.dist-info/licenses/LICENSE
adafruit_mcp3421/__init__.py
adafruit_mcp3421/analog_in.py
adafruit_mcp3421/mcp3421.py
adafruit_circuitpython_mcp3421-1.1.5.dist-info/METADATA
adafruit_circuitpython_mcp3421-1.1.5.dist-info/WHEEL
adafruit_circuitpython_mcp3421-1.1.5.dist-info/top_level.txt
adafruit_circuitpython_mcp3421-1.1.5.dist-info/RECORD
